{
  "users": {
    "603182413660684321": {
      "count": 4,
      "lastOffenseAt": 1777384480176,
      "muteUntil": 1777388080176,
      "lastWord": "หี",
      "lastSource": "chat"
    },
    "946756535936233542": {
      "count": 2,
      "lastOffenseAt": 1777384410234,
      "muteUntil": 0,
      "lastWord": "หี",
      "lastSource": "chat"
    },
    "967120879689551873": {
      "count": 2,
      "lastOffenseAt": 1777384379910,
      "muteUntil": 0,
      "lastWord": "หี",
      "lastSource": "chat"
    }
  }
}
